libra/__init__.py
libra/access_path.py
libra/account.py
libra/account_address.py
libra/account_config.py
libra/account_resource.py
libra/account_state.py
libra/account_state_blob.py
libra/block_info.py
libra/block_metadata.py
libra/bytecode.py
libra/contract_event.py
libra/discovery_info.py
libra/discovery_set.py
libra/epoch_change.py
libra/epoch_info.py
libra/event.py
libra/get_with_proof.py
libra/hasher.py
libra/identifier.py
libra/json_print.py
libra/language_storage.py
libra/ledger_info.py
libra/libra_timestamp.py
libra/mint.key
libra/move_resource.py
libra/proto_helper.py
libra/rustlib.py
libra/transaction_scripts.py
libra/validator_config.py
libra/validator_info.py
libra/validator_signer.py
libra/validator_verifier.py
libra/version.py
libra/vm_error.py
libra/waypoint.py
libra/crypto/__init__.py
libra/crypto/ed25519.py
libra/crypto/multi_ed25519.py
libra/crypto/x25519.py
libra/error/__init__.py
libra/error/ac_error.py
libra/error/mempool_error.py
libra/on_chain_config/__init__.py
libra/on_chain_config/libra_version.py
libra/on_chain_config/mod.py
libra/on_chain_config/on_chain_config.py
libra/on_chain_config/validator_set.py
libra/on_chain_config/vm_publishing_option.py
libra/proof/__init__.py
libra/proof/account_state_with_proof.py
libra/proof/accumulator.py
libra/proof/definition.py
libra/proof/event_with_proof.py
libra/proof/merkle_tree.py
libra/proof/mod.py
libra/proof/position.py
libra/proof/transaction_list_with_proof.py
libra/proof/transaction_with_proof.py
libra/transaction/__init__.py
libra/transaction/authenticator.py
libra/transaction/change_set.py
libra/transaction/mod.py
libra/transaction/module.py
libra/transaction/raw_transaction.py
libra/transaction/script.py
libra/transaction/signed_transaction.py
libra/transaction/transaction.py
libra/transaction/transaction_argument.py
libra/transaction/transaction_info.py
libra/transaction/transaction_payload.py
libra/transaction/write_set.py
libra_core-0.9.7.dist-info/LICENSE
libra_core-0.9.7.dist-info/METADATA
libra_core-0.9.7.dist-info/WHEEL
libra_core-0.9.7.dist-info/top_level.txt
libra_core-0.9.7.dist-info/RECORD
