Metadata-Version: 2.1
Name: libra-core
Version: 0.9.7
Summary: Libra core types and functions for python
Home-page: https://github.com/MoveOnLibra/libra-core.git
Author: yuan xinyu
Author-email: yuan_xin_yu@hotmail.com
License: UNKNOWN
Platform: UNKNOWN
Classifier: Programming Language :: Python :: 3
Classifier: License :: OSI Approved :: MIT License
Classifier: Operating System :: OS Independent
Requires-Python: >=3.7
Requires-Dist: canoser (>=0.8.2)
Requires-Dist: PyNaCl
